{
	"items": [
		{
			"name": ".NET",
			"title": ".NET",
			"type": "Framework",
			"value": 0,
			"iconCss": "",
			"projects": 26,
			"jobs": 0,
			"orderindex": 1,
			"ismajor": true
		},
		{
			"name": ".NETCore",
			"title": ".NETCore",
			"type": "Framework",
			"value": 0,
			"iconCss": "",
			"projects": 8,
			"jobs": 0,
			"ismajor": true,
			"orderindex": 1
		},
		{
			"name": "Java",
			"title": "Java",
			"type": "Programming Language",
			"value": 0,
			"iconCss": "",
			"projects": 3,
			"jobs": 0,
			"ismajor": true,
			"orderindex": 2
		},
		{
			"name": "C#",
			"title": "C#",
			"type": "Language",
			"value": 0,
			"iconCss": "",
			"projects": 32,
			"jobs": 0,
			"orderindex": 3,
			"ismajor": true
		},
		{
			"name": "Typescript",
			"title": "Typescript",
			"type": "Frontend",
			"value": 0,
			"iconCss": "",
			"projects": 3,
			"jobs": 0,
			"ismajor": true,
			"orderindex": 4
		},
		{
			"name": "AngularJS",
			"title": "AngularJS",
			"type": "Frontend",
			"value": 0,
			"iconCss": "",
			"projects": 10,
			"jobs": 0,
			"ismajor": true,
			"orderindex": 5
		},
		{
			"name": "Angular",
			"title": "Angular",
			"type": "Frontend",
			"value": 0,
			"iconCss": "",
			"projects": 3,
			"jobs": 0,
			"ismajor": true,
			"orderindex": 5
		},
		{
			"name": "Docker",
			"title": "Docker",
			"type": "Virtualization",
			"value": 0,
			"iconCss": "",
			"projects": 8,
			"jobs": 0,
			"ismajor": true,
			"orderindex": 6
		},
		{
			"name": "Gitlab",
			"title": "Gitlab",
			"type": "Source Control",
			"value": 0,
			"iconCss": "",
			"projects": 11,
			"jobs": 0,
			"ismajor": true,
			"orderindex": 7
		},
		{
			"name": "Jenkins",
			"title": "Jenkins",
			"type": "DevOps",
			"value": 0,
			"iconCss": "",
			"projects": 11,
			"jobs": 0,
			"ismajor": true,
			"orderindex": 8
		},
		{
			"name": "HTML5",
			"title": "HTML5",
			"type": "Frontend",
			"value": 0,
			"iconCss": "",
			"projects": 45,
			"jobs": 0,
			"ismajor": true
		},
		{
			"name": "JS",
			"title": "JS",
			"type": "Frontend",
			"value": 0,
			"iconCss": "",
			"projects": 45,
			"jobs": 0,
			"ismajor": true
		},
		{
			"name": "CSS",
			"title": "CSS",
			"type": "Frontend",
			"value": 0,
			"iconCss": "",
			"projects": 33,
			"jobs": 0,
			"ismajor": true
		},
		{
			"name": "MS SQL",
			"title": "MS SQL",
			"type": "Database",
			"value": 0,
			"iconCss": "",
			"projects": 29,
			"jobs": 0,
			"ismajor": true
		},
		{
			"name": "MS Project",
			"title": "MS Project",
			"type": "Project Management",
			"value": 0,
			"iconCss": "",
			"projects": 3,
			"jobs": 0,
			"ismajor": true
		},
		{
			"name": "Nodejs",
			"title": "Nodejs",
			"type": "Backend",
			"value": 0,
			"iconCss": "",
			"projects": 2,
			"jobs": 0,
			"ismajor": true
		},
		{
			"name": "Ionic",
			"title": "Ionic",
			"type": "Frontend",
			"value": 0,
			"iconCss": "",
			"projects": 2,
			"jobs": 0,
			"ismajor": true
		},
		{
			"name": "Photoshop",
			"title": "Photoshop",
			"type": "Graphics Design",
			"value": 0,
			"iconCss": "",
			"projects": 44,
			"jobs": 0
		},
		{
			"name": "ASP.NET",
			"title": "ASP.NET",
			"type": "Web",
			"value": 0,
			"iconCss": "",
			"projects": 17,
			"jobs": 0
		},
		{
			"name": "LINQ",
			"title": "LINQ",
			"type": "Database",
			"value": 0,
			"iconCss": "",
			"projects": 16,
			"jobs": 0
		},
		{
			"name": "CSS3",
			"title": "CSS3",
			"type": "Frontend",
			"value": 0,
			"iconCss": "",
			"projects": 12,
			"jobs": 0
		},
		{
			"name": "TFS",
			"title": "TFS",
			"type": "Source Control",
			"value": 0,
			"iconCss": "",
			"projects": 11,
			"jobs": 0
		},
		{
			"name": "JQuery",
			"title": "JQuery",
			"type": "Frontend",
			"value": 0,
			"iconCss": "",
			"projects": 11,
			"jobs": 0
		},
		{
			"name": "Git",
			"title": "Git",
			"type": "Source Control",
			"value": 0,
			"iconCss": "",
			"projects": 9,
			"jobs": 0
		},
		{
			"name": "ASP.NET MVC",
			"title": "ASP.NET MVC",
			"type": "Web",
			"value": 0,
			"iconCss": "",
			"projects": 9,
			"jobs": 0
		},
		{
			"name": "Hangfire",
			"title": "Hangfire",
			"type": "Scheduled Tasks",
			"value": 0,
			"iconCss": "",
			"projects": 9,
			"jobs": 0
		},
		{
			"name": "Entity Framework Core",
			"title": "Entity Framework Core",
			"type": "ORM",
			"value": 0,
			"iconCss": "",
			"projects": 9,
			"jobs": 0
		},
		{
			"name": "MySQL",
			"title": "MySQL",
			"type": "Database",
			"value": 0,
			"iconCss": "",
			"projects": 8,
			"jobs": 0
		},
		{
			"name": "PHP",
			"title": "PHP",
			"type": "Backend",
			"value": 0,
			"iconCss": "",
			"projects": 8,
			"jobs": 0
		},
		{
			"name": "npm",
			"title": "npm",
			"type": "Dependency Management",
			"value": 0,
			"iconCss": "",
			"projects": 8,
			"jobs": 0
		},
		{
			"name": "NuGet",
			"title": "NuGet",
			"type": "Dependency Management",
			"value": 0,
			"iconCss": "",
			"projects": 8,
			"jobs": 0
		},
		{
			"name": "ProGet",
			"title": "ProGet",
			"type": "Dependency Management",
			"value": 0,
			"iconCss": "",
			"projects": 8,
			"jobs": 0
		},
		{
			"name": "Visual Studio",
			"title": "Visual Studio",
			"type": "IDE",
			"value": 0,
			"iconCss": "",
			"projects": 8,
			"jobs": 0
		},
		{
			"name": "Oracle",
			"title": "Oracle",
			"type": "Database",
			"value": 0,
			"iconCss": "",
			"projects": 7,
			"jobs": 0
		},
		{
			"name": "Telerik UI for Silverlight",
			"title": "Telerik UI for Silverlight",
			"type": "Web",
			"value": 0,
			"iconCss": "",
			"projects": 7,
			"jobs": 0
		},
		{
			"name": "Silverlight",
			"title": "Silverlight",
			"type": "Web",
			"value": 0,
			"iconCss": "",
			"projects": 7,
			"jobs": 0
		},
		{
			"name": "WCF",
			"title": "WCF",
			"type": "Webservices",
			"value": 0,
			"iconCss": "",
			"projects": 7,
			"jobs": 0
		},
		{
			"name": "EntityFramework",
			"title": "EntityFramework",
			"type": "ORM",
			"value": 0,
			"iconCss": "",
			"projects": 7,
			"jobs": 0
		},
		{
			"name": "Fiddler",
			"title": "Fiddler",
			"type": "Sniffing Tool",
			"value": 0,
			"iconCss": "",
			"projects": 7,
			"jobs": 0
		},
		{
			"name": "XAML",
			"title": "XAML",
			"type": "File Format",
			"value": 0,
			"iconCss": "",
			"projects": 7,
			"jobs": 0
		},
		{
			"name": "MVVM",
			"title": "MVVM",
			"type": "Design Pattern",
			"value": 0,
			"iconCss": "",
			"projects": 7,
			"jobs": 0
		},
		{
			"name": "MS Blend",
			"title": "MS Blend",
			"type": "Graphics Design",
			"value": 0,
			"iconCss": "",
			"projects": 7,
			"jobs": 0
		},
		{
			"name": "PDFWCore",
			"title": "PDFWCore",
			"type": "Framework",
			"value": 0,
			"iconCss": "",
			"projects": 6,
			"jobs": 0
		},
		{
			"name": "Pascal",
			"title": "Pascal",
			"type": "Programming Language",
			"value": 0,
			"iconCss": "",
			"projects": 5,
			"jobs": 0
		},
		{
			"name": "XML",
			"title": "XML",
			"type": "File Format",
			"value": 0,
			"iconCss": "",
			"projects": 5,
			"jobs": 0
		},
		{
			"name": "Adobe Flash",
			"title": "Adobe Flash",
			"type": "Graphics Design",
			"value": 0,
			"iconCss": "",
			"projects": 3,
			"jobs": 0
		},
		{
			"name": "Redmine",
			"title": "Redmine",
			"type": "Project Management",
			"value": 0,
			"iconCss": "",
			"projects": 3,
			"jobs": 0
		},
		{
			"name": "Azure",
			"title": "Azure",
			"type": "Cloud Hosting",
			"value": 0,
			"iconCss": "",
			"projects": 3,
			"jobs": 0
		},
		{
			"name": "SOAP",
			"title": "SOAP",
			"type": "Web Services",
			"value": 0,
			"iconCss": "",
			"projects": 3,
			"jobs": 0
		},
		{
			"name": "VB.NET",
			"title": "VB.NET",
			"type": "Backend",
			"value": 0,
			"iconCss": "",
			"projects": 3,
			"jobs": 0
		},
		{
			"name": "Bootstrap",
			"title": "Bootstrap",
			"type": "Frontend",
			"value": 0,
			"iconCss": "",
			"projects": 3,
			"jobs": 0
		},
		{
			"name": "DB2",
			"title": "DB2",
			"type": "Database",
			"value": 0,
			"iconCss": "",
			"projects": 2,
			"jobs": 0
		},
		{
			"name": "Bash Scripting",
			"title": "Bash Scripting",
			"type": "Scripting",
			"value": 0,
			"iconCss": "",
			"projects": 2,
			"jobs": 0
		},
		{
			"name": "Nexus",
			"title": "Nexus",
			"type": "Dependency Management",
			"value": 0,
			"iconCss": "",
			"projects": 2,
			"jobs": 0
		},
		{
			"name": "Source Tree",
			"title": "Source Tree",
			"type": "Source Control",
			"value": 0,
			"iconCss": "",
			"projects": 2,
			"jobs": 0
		},
		{
			"name": "Tortoise Hg",
			"title": "Tortoise Hg",
			"type": "Source Control",
			"value": 0,
			"iconCss": "",
			"projects": 2,
			"jobs": 0
		},
		{
			"name": "ubuntu",
			"title": "ubuntu",
			"type": "OS",
			"value": 0,
			"iconCss": "",
			"projects": 2,
			"jobs": 0
		},
		{
			"name": "Apache Ant",
			"title": "Apache Ant",
			"type": "Task Runner",
			"value": 0,
			"iconCss": "",
			"projects": 2,
			"jobs": 0
		},
		{
			"name": "Visual Basic",
			"title": "Visual Basic",
			"type": "Programming Language",
			"value": 0,
			"iconCss": "",
			"projects": 2,
			"jobs": 0
		},
		{
			"name": "VMware",
			"title": "VMware",
			"type": "Virtualization",
			"value": 0,
			"iconCss": "",
			"projects": 2,
			"jobs": 0
		},
		{
			"name": "Express",
			"title": "Express",
			"type": "Backend",
			"value": 0,
			"iconCss": "",
			"projects": 2,
			"jobs": 0
		},
		{
			"name": "EJS",
			"title": "EJS",
			"type": "Backend",
			"value": 0,
			"iconCss": "",
			"projects": 2,
			"jobs": 0
		},
		{
			"name": "3Ds Max",
			"title": "3Ds Max",
			"type": "3D Modeling Tool",
			"value": 0,
			"iconCss": "",
			"projects": 2,
			"jobs": 0
		},
		{
			"name": "Scorm",
			"title": "Scorm",
			"type": "E-Learning Standart",
			"value": 0,
			"iconCss": "",
			"projects": 2,
			"jobs": 0
		},
		{
			"name": "MS Access",
			"title": "MS Access",
			"type": "Database",
			"value": 0,
			"iconCss": "",
			"projects": 2,
			"jobs": 0
		},
		{
			"name": "iReports",
			"title": "iReports",
			"type": "Reporting",
			"value": 0,
			"iconCss": "",
			"projects": 2,
			"jobs": 0
		},
		{
			"name": "VB Script",
			"title": "VB Script",
			"type": "Programming Language",
			"value": 0,
			"iconCss": "",
			"projects": 2,
			"jobs": 0
		},
		{
			"name": "Jasper Reports",
			"title": "Jasper Reports",
			"type": "Reporting",
			"value": 0,
			"iconCss": "",
			"projects": 2,
			"jobs": 0
		},
		{
			"name": "Jasper BI",
			"title": "Jasper BI",
			"type": "Business Intelligence",
			"value": 0,
			"iconCss": "",
			"projects": 2,
			"jobs": 0
		},
		{
			"name": "Animate.css",
			"title": "Animate.css",
			"type": "Frontend",
			"value": 0,
			"iconCss": "",
			"projects": 2,
			"jobs": 0
		},
		{
			"name": "HyperV",
			"title": "HyperV",
			"type": "Virtualization",
			"value": 0,
			"iconCss": "",
			"projects": 2,
			"jobs": 0
		},
		{
			"name": "Mercurial",
			"title": "Mercurial",
			"type": "Source Control",
			"value": 0,
			"iconCss": "",
			"projects": 2,
			"jobs": 0
		},
		{
			"name": "Spring",
			"title": "Spring",
			"type": "Framework",
			"value": 0,
			"iconCss": "",
			"projects": 2,
			"jobs": 0
		},
		{
			"name": "Hibernate",
			"title": "Hibernate",
			"type": "ORM",
			"value": 0,
			"iconCss": "",
			"projects": 2,
			"jobs": 0
		},
		{
			"name": "WPF",
			"title": "WPF",
			"type": "Desktop",
			"value": 0,
			"iconCss": "",
			"projects": 2,
			"jobs": 0
		},
		{
			"name": "Eclipse",
			"title": "Eclipse",
			"type": "IDE",
			"value": 0,
			"iconCss": "",
			"projects": 2,
			"jobs": 0
		},
		{
			"name": "Oracle BI",
			"title": "Oracle BI",
			"type": "Business Intelligence",
			"value": 0,
			"iconCss": "",
			"projects": 2,
			"jobs": 0
		},
		{
			"name": "AWS",
			"title": "AWS",
			"type": "Cloud Hosting",
			"value": 0,
			"iconCss": "",
			"projects": 2,
			"jobs": 0
		},
		{
			"name": "SQL Lite",
			"title": "SQL Lite",
			"type": "Database",
			"value": 0,
			"iconCss": "",
			"projects": 2,
			"jobs": 0
		},
		{
			"name": "My SQL",
			"title": "My SQL",
			"type": "Database",
			"value": 0,
			"iconCss": "",
			"projects": 2,
			"jobs": 0
		},
		{
			"name": "Timelinejs3",
			"title": "Timelinejs3",
			"type": "Frontend",
			"value": 0,
			"iconCss": "",
			"projects": 2,
			"jobs": 0
		},
		{
			"name": "Json",
			"title": "Json",
			"type": "File Format",
			"value": 0,
			"iconCss": "",
			"projects": 2,
			"jobs": 0
		},
		{
			"name": "APM",
			"title": "APM",
			"type": "Project Management",
			"value": 0,
			"iconCss": "",
			"projects": 2,
			"jobs": 0
		},
		{
			"name": "Heroku",
			"title": "Heroku",
			"type": "Cloud Hosting",
			"value": 0,
			"iconCss": "",
			"projects": 1,
			"jobs": 0
		},
		{
			"name": "Paypal",
			"title": "Paypal",
			"type": "E-Commerce",
			"value": 0,
			"iconCss": "",
			"projects": 1,
			"jobs": 0
		},
		{
			"name": "Microsoft Dynamics NAV",
			"title": "Microsoft Dynamics NAV",
			"type": "ERP",
			"value": 0,
			"iconCss": "",
			"projects": 1,
			"jobs": 0
		},
		{
			"name": "PDFW",
			"title": "PDFW",
			"type": "Framework",
			"value": 0,
			"iconCss": "",
			"projects": 1,
			"jobs": 0
		},
		{
			"name": "Alibaba Cloud",
			"title": "Alibaba Cloud",
			"type": "Cloud Hosting",
			"value": 0,
			"iconCss": "",
			"projects": 1,
			"jobs": 0
		},
		{
			"name": "Google Cloud",
			"title": "Google Cloud",
			"type": "Cloud Hosting",
			"value": 0,
			"iconCss": "",
			"projects": 1,
			"jobs": 0
		},
		{
			"name": "dom-to-image",
			"title": "dom-to-image",
			"type": "Frontend",
			"value": 0,
			"iconCss": "",
			"projects": 1,
			"jobs": 0
		},
		{
			"name": "jspdf",
			"title": "jspdf",
			"type": "Frontend",
			"value": 0,
			"iconCss": "",
			"projects": 1,
			"jobs": 0
		},
		{
			"name": "Windows Forms",
			"title": "Windows Forms",
			"type": "Frontend",
			"value": 0,
			"iconCss": "",
			"projects": 1,
			"jobs": 0
		},
		{
			"name": "Digital Ocean",
			"title": "Digital Ocean",
			"type": "Cloud Hosting",
			"value": 0,
			"iconCss": "",
			"projects": 1,
			"jobs": 0
		},
		{
			"name": "Adobe Atmosphere",
			"title": "Adobe Atmosphere",
			"type": "Gaming Engine",
			"value": 0,
			"iconCss": "",
			"projects": 1,
			"jobs": 0
		},
		{
			"name": "Fontawesome",
			"title": "Fontawesome",
			"type": "Frontend",
			"value": 0,
			"iconCss": "",
			"projects": 1,
			"jobs": 0
		},
		{
			"name": "Dark Basic",
			"title": "Dark Basic",
			"type": "Gaming Engine",
			"value": 0,
			"iconCss": "",
			"projects": 1,
			"jobs": 0
		},
		{
			"name": "MomentJS",
			"title": "MomentJS",
			"type": "Frontend",
			"value": 0,
			"iconCss": "",
			"projects": 1,
			"jobs": 0
		},
		{
			"name": "PrimeNG",
			"title": "PrimeNG",
			"type": "Frontend",
			"value": 0,
			"iconCss": "",
			"projects": 1,
			"jobs": 0
		},
		{
			"name": "Angular Material",
			"title": "Angular Material",
			"type": "Frontend",
			"value": 0,
			"iconCss": "",
			"projects": 1,
			"jobs": 0
		},
		{
			"name": "Github",
			"title": "Github",
			"type": "Source Control",
			"value": 0,
			"iconCss": "",
			"projects": 1,
			"jobs": 0
		},
		{
			"name": "VisualBasic.NET",
			"title": "VisualBasic.NET",
			"type": "Programming Language",
			"value": 0,
			"iconCss": "",
			"projects": 1,
			"jobs": 0
		},
		{
			"name": "Design Patterns",
			"title": "Design Patterns",
			"type": "Approach",
			"value": 0,
			"iconCss": "",
			"projects": 1,
			"jobs": 0
		}
	],
	"types": [
		{
			"name": "Frontend",
			"title": "Frontend",
			"items": 19
		},
		{
			"name": "Graphics Design",
			"title": "Graphics Design",
			"items": 3
		},
		{
			"name": "Language",
			"title": "Language",
			"items": 1
		},
		{
			"name": "Database",
			"title": "Database",
			"items": 8
		},
		{
			"name": "Framework",
			"title": "Framework",
			"items": 5
		},
		{
			"name": "Web",
			"title": "Web",
			"items": 4
		},
		{
			"name": "Source Control",
			"title": "Source Control",
			"items": 7
		},
		{
			"name": "DevOps",
			"title": "DevOps",
			"items": 1
		},
		{
			"name": "ORM",
			"title": "ORM",
			"items": 3
		},
		{
			"name": "Scheduled Tasks",
			"title": "Scheduled Tasks",
			"items": 1
		},
		{
			"name": "Backend",
			"title": "Backend",
			"items": 5
		},
		{
			"name": "Dependency Management",
			"title": "Dependency Management",
			"items": 4
		},
		{
			"name": "Virtualization",
			"title": "Virtualization",
			"items": 3
		},
		{
			"name": "IDE",
			"title": "IDE",
			"items": 2
		},
		{
			"name": "Design Pattern",
			"title": "Design Pattern",
			"items": 1
		},
		{
			"name": "File Format",
			"title": "File Format",
			"items": 3
		},
		{
			"name": "Webservices",
			"title": "Webservices",
			"items": 1
		},
		{
			"name": "Sniffing Tool",
			"title": "Sniffing Tool",
			"items": 1
		},
		{
			"name": "Programming Language",
			"title": "Programming Language",
			"items": 5
		},
		{
			"name": "Project Management",
			"title": "Project Management",
			"items": 3
		},
		{
			"name": "Cloud Hosting",
			"title": "Cloud Hosting",
			"items": 6
		},
		{
			"name": "Web Services",
			"title": "Web Services",
			"items": 1
		},
		{
			"name": "Scripting",
			"title": "Scripting",
			"items": 1
		},
		{
			"name": "OS",
			"title": "OS",
			"items": 1
		},
		{
			"name": "Task Runner",
			"title": "Task Runner",
			"items": 1
		},
		{
			"name": "3D Modeling Tool",
			"title": "3D Modeling Tool",
			"items": 1
		},
		{
			"name": "E-Learning Standart",
			"title": "E-Learning Standart",
			"items": 1
		},
		{
			"name": "Reporting",
			"title": "Reporting",
			"items": 2
		},
		{
			"name": "Business Intelligence",
			"title": "Business Intelligence",
			"items": 2
		},
		{
			"name": "Desktop",
			"title": "Desktop",
			"items": 1
		},
		{
			"name": "E-Commerce",
			"title": "E-Commerce",
			"items": 1
		},
		{
			"name": "ERP",
			"title": "ERP",
			"items": 1
		},
		{
			"name": "Gaming Engine",
			"title": "Gaming Engine",
			"items": 2
		},
		{
			"name": "Approach",
			"title": "Approach",
			"items": 1
		}
	]
}